{"248001":["IN","248001","Mothrowala","Uttarakhand","39","Dehradun","060","Dehradun","","30.3213","78.04","3"],"248002":["IN","248002","Mohbewala","Uttarakhand","39","Dehradun","060","Dehradun","","30.2796","78.1467","1"],"248003":["IN","248003","Chauki Dhaulas","Uttarakhand","39","Dehradun","060","Vikasnagar **","","30.365","78.0338","3"],"248005":["IN","248005","I.I.P.","Uttarakhand","39","Dehradun","060","Dehradun","","30.2731","78.0825","3"],"248006":["IN","248006","I.N.C.","Uttarakhand","39","Dehradun","060","Dehradun","","30.2796","78.1467","1"],"248007":["IN","248007","Chandanwari","Uttarakhand","39","Dehradun","060","Vikasnagar","","30.2266","78.1393","3"],"248008":["IN","248008","Raipur(O.F)","Uttarakhand","39","Dehradun","060","Dehradun","","30.2008","78.4304","3"],"248009":["IN","248009","Bhagwantpur","Uttarakhand","39","Dehradun","060","Dehradun","","30.4085","78.0722","4"],"248011":["IN","248011","Selaqui","Uttarakhand","39","Dehradun","060","Dehradun","","30.2743","78.1823","1"],"248012":["IN","248012","Defence Colony","Uttarakhand","39","Dehradun","060","Dehradun","","30.2798","78.0545","4"],"248013":["IN","248013","Sahastradhara Road","Uttarakhand","39","Dehradun","060","Dehradun","","30.1623","78.4813","3"],"248014":["IN","248014","Shamshergarh","Uttarakhand","39","Dehradun","060","Dehradun","","30.2852","78.083","3"],"248015":["IN","248015","Sudhowala","Uttarakhand","39","Dehradun","060","Dehradun","","30.2743","78.1823","1"],"248016":["IN","248016","Jollygrant","Uttarakhand","39","Dehradun","060","Dehradun","","30.2743","78.1823","1"],"248018":["IN","248018","Mehunwala","Uttarakhand","39","Dehradun","060","Dehradun","","30.4819","77.8114","4"],"248121":["IN","248121","Banjarawala","Uttarakhand","39","Dehradun","060","Dehradun","","30.6713","77.8947","1"],"248122":["IN","248122","Barlowganj","Uttarakhand","39","Dehradun","060","Dehradun","","30.4409","78.0892","4"],"248123":["IN","248123","Marlau","Uttarakhand","39","Dehradun","060","Chakrata","","30.7198","77.8572","3"],"248124":["IN","248124","Khabau","Uttarakhand","39","Dehradun","060","Chakrata","","30.6908","77.9668","3"],"248125":["IN","248125","Ashok Ashram","Uttarakhand","39","Dehradun","060","NA","","30.4813","77.8589","3"],"248140":["IN","248140","Nagal Bulandawala","Uttarakhand","39","Dehradun","060","Dehradun","","30.23","78.0734","3"],"248142":["IN","248142","Jassowala","Uttarakhand","39","Dehradun","060","Vikasnagar","","30.4249","77.7698","3"],"248143":["IN","248143","Sangaon","Uttarakhand","39","Dehradun","060","Rishikesh","","30.2401","78.2349","4"],"248145":["IN","248145","Dandi","Uttarakhand","39","Dehradun","060","Rishikesh","","30.3541","78.0315","4"],"248146":["IN","248146","Seemadwar","Uttarakhand","39","Dehradun","060","Dehradun","","30.3107","78.0182","1"],"248158":["IN","248158","Laksyar","Uttarakhand","39","Dehradun","060","Chakrata","","30.5832","77.9286","3"],"248159":["IN","248159","Chhibroo","Uttarakhand","39","Dehradun","060","Chakrata","","30.4904","77.7837","3"],"248165":["IN","248165","Ubhreau","Uttarakhand","39","Dehradun","060","Chakrata","","30.6225","77.833","3"],"248171":["IN","248171","Kanwali","Uttarakhand","39","Dehradun","060","Dehradun","","30.2937","78.0035","3"],"248179":["IN","248179","Naa","Uttarakhand","39","Dehradun","060","Dehradun","","30.4395","78.0793","3"],"248195":["IN","248195","I.P.E.","Uttarakhand","39","Dehradun","060","Dehradun","","30.44","77.9836","1"],"248196":["IN","248196","Bullard","Uttarakhand","39","Dehradun","060","Chakrata","","30.5968","78.0026","3"],"248197":["IN","248197","Dobhri","Uttarakhand","39","Dehradun","060","Vikasnagar","","30.2987","78.0292","3"],"248198":["IN","248198","Wht-I","Uttarakhand","39","Dehradun","060","Vikasnagar","","30.4649","77.7811","3"],"248199":["IN","248199","Bhagwat","Uttarakhand","39","Dehradun","060","Tuini","","30.8621","77.8182","3"]}